talus_aws_utils/__init__.py
talus_aws_utils/lambda_.py
talus_aws_utils/py.typed
talus_aws_utils/s3.py
talus_aws_utils/secrets.py
talus_aws_utils-0.0.9.dist-info/LICENSE.rst
talus_aws_utils-0.0.9.dist-info/WHEEL
talus_aws_utils-0.0.9.dist-info/METADATA
talus_aws_utils-0.0.9.dist-info/RECORD
