Metadata-Version: 2.1
Name: talus-aws-utils
Version: 0.0.9
Summary: Talus AWS Utils
Home-page: https://github.com/rmeinl/talus-aws-utils
License: MIT
Author: Rico Meinl
Author-email: rmeinl@talus.bio
Requires-Python: >=3.7.1,<4.0.0
Classifier: License :: OSI Approved :: MIT License
Classifier: Programming Language :: Python :: 3
Classifier: Programming Language :: Python :: 3.7
Classifier: Programming Language :: Python :: 3.8
Classifier: Programming Language :: Python :: 3.9
Requires-Dist: boto3 (>=1.17.106,<2.0.0)
Requires-Dist: hurry.filesize (>=0.9,<0.10)
Requires-Dist: joblib (>=1.0.1,<2.0.0)
Requires-Dist: pandas (>=1.3.0,<2.0.0)
Requires-Dist: pyarrow (>=4.0.1,<5.0.0)
Project-URL: Changelog, https://github.com/rmeinl/talus-aws-utils/releases
Project-URL: Documentation, https://talus-aws-utils.readthedocs.io
Project-URL: Repository, https://github.com/rmeinl/talus-aws-utils
